aporacle/__init__.py
aporacle/base/__init__.py
aporacle/conf/__init__.py
aporacle/core/__init__.py
aporacle/core/utils/__init__.py
aporacle/core/utils/async_call_scheduler.py
aporacle/data/__init__.py
aporacle/data/asset/__init__.py
aporacle/data/aws/__init__.py
aporacle/data/combination.py
aporacle/data/db/__init__.py
aporacle/data/db/crud.py
aporacle/data/db/mongo/__init__.py
aporacle/data/db/mongo/mongo_connection_manager.py
aporacle/data/db/sql/__init__.py
aporacle/data/db/sql/data_view_base.py
aporacle/data/db/sql/models/__init__.py
aporacle/data/db/sql/models/ensembled.py
aporacle/data/db/sql/models/evaluated_feed.py
aporacle/data/db/sql/models/evaluated_model.py
aporacle/data/db/sql/models/evaluation.py
aporacle/data/db/sql/models/feed.py
aporacle/data/db/sql/models/feed_result.py
aporacle/data/db/sql/models/metadata.py
aporacle/data/db/sql/models/models.py
aporacle/data/db/sql/models/prediction.py
aporacle/data/db/sql/models/prepared_symbol.py
aporacle/data/db/sql/models/provider.py
aporacle/data/db/sql/models/submission.py
aporacle/data/db/sql/models/symbol.py
aporacle/data/db/sql/models/tick.py
aporacle/data/db/sql/models/trained_model.py
aporacle/data/db/sql/models/transaction.py
aporacle/data/db/sql/models/voter.py
aporacle/data/feed_results.py
aporacle/data/gcp/__init__.py
aporacle/data/symbols/__init__.py
aporacle/execution/__init__.py
aporacle/execution/executables.py
aporacle/network/__init__.py
aporacle/network/network_base.py
aporacle/runnables/base.py
aporacle/runnables/runnable_base.py
aporacle/shared_setup.py
aporacle-0.0.197.dist-info/METADATA
aporacle-0.0.197.dist-info/WHEEL
aporacle-0.0.197.dist-info/RECORD
