Metadata-Version: 2.1
Name: aporacle
Version: 0.0.197
Summary: 
Author: Makhosonke Morafo
Author-email: makhosonke@komokun.org
Requires-Python: >=3.9,<3.11
Classifier: Programming Language :: Python :: 3
Classifier: Programming Language :: Python :: 3.9
Classifier: Programming Language :: Python :: 3.10
Requires-Dist: aiomysql (>=0.2.0,<0.3.0)
Requires-Dist: cachetools (>=5.3.3,<6.0.0)
Requires-Dist: komoutils (>=0.0.235,<0.0.236)
Requires-Dist: mysqlclient (>=2.2.4,<3.0.0)
Requires-Dist: pandas (>=2.2.1,<3.0.0)
Requires-Dist: sqlalchemy (>=2.0.34,<3.0.0)
Requires-Dist: websockets (>=13.0.1,<14.0.0)
